Workbook

Sheet Dashboard
B2: 📈 Summary Dashboard
B4: KEY PERFORMANCE INDICATORS
B5: Total Employees | D5: Avg Base Salary (NPR) | F5: Total Comp Paid (NPR) | H5: Avg Performance | J5: Avg Attendance | L5: Total Projects Done
B7: ='Employee Database'!A503 -> TOTALS / AVERAGES | D7: ='Employee Database'!I503 -> 140280 | F7: ='Employee Database'!L503 -> 82839263 | H7: ='Employee Database'!N503 -> 3.69766 | J7: ='Employee Database'!O503 -> 0.860214 | L7: ='Employee Database'!P503 -> 10301
B11: Total Sales (NPR) | D11: Total Net Revenue (NPR) | F11: Gross Profit (NPR) | H11: Total Units Sold | J11: Total Returns | L11: COGS Total (NPR)
B13: ='Monthly Sales'!J303 -> 712485479 | D13: ='Monthly Sales'!O303 -> 6.5966148e+08 | F13: ='Monthly Sales'!L303 -> 3.0434895e+08 | H13: ='Monthly Sales'!H303 -> 72621 | J13: ='Monthly Sales'!P303 -> 1833 | L13: ='Monthly Sales'!K303 -> 4.0813653e+08
B17: Total Students | D17: Avg Percentage | F17: Avg GPA | H17: Avg Attendance | J17: Total Stock Value | L17: Total Assets
B19: =COUNTA('Student Records'!A3:A402) -> 400 | D19: ='Student Records'!M403 -> 59.615 | F19: ='Student Records'!O403 -> 2.143 | H19: ='Student Records'!P403 -> 0.7638225 | J19: =Inventory!J253 -> 3606432600 | L19: =Inventory!T253 -> 3827058500
B23: DEPARTMENT HEADCOUNT (from Employee DB)
B24: Department | C24: Headcount | D24: Avg Salary (NPR) | E24: Total Comp (NPR) | F24: Avg Performance
B25: Engineering | C25: =COUNTIF('Employee Database'!C3:C502,"Engineering") -> 33 | D25: =AVERAGEIF('Employee Database'!C3:C502,B25,'Employee Database'!I3:I502) -> 133121.21 | E25: =SUMIF('Employee Database'!C3:C502,B25,'Employee Database'!L3:L502) -> 5170392 | F25: =AVERAGEIF('Employee Database'!C3:C502,B25,'Employee Database'!N3:N502) -> 3.630303
B26: Sales | C26: =COUNTIF('Employee Database'!C3:C502,"Sales") -> 52 | D26: =AVERAGEIF('Employee Database'!C3:C502,B26,'Employee Database'!I3:I502) -> 124423.08 | E26: =SUMIF('Employee Database'!C3:C502,B26,'Employee Database'!L3:L502) -> 7601981 | F26: =AVERAGEIF('Employee Database'!C3:C502,B26,'Employee Database'!N3:N502) -> 3.6907692
B27: Marketing | C27: =COUNTIF('Employee Database'!C3:C502,"Marketing") -> 53 | D27: =AVERAGEIF('Employee Database'!C3:C502,B27,'Employee Database'!I3:I502) -> 146245.28 | E27: =SUMIF('Employee Database'!C3:C502,B27,'Employee Database'!L3:L502) -> 9055469 | F27: =AVERAGEIF('Employee Database'!C3:C502,B27,'Employee Database'!N3:N502) -> 3.68
B28: HR | C28: =COUNTIF('Employee Database'!C3:C502,"HR") -> 48 | D28: =AVERAGEIF('Employee Database'!C3:C502,B28,'Employee Database'!I3:I502) -> 152083.33 | E28: =SUMIF('Employee Database'!C3:C502,B28,'Employee Database'!L3:L502) -> 8555174 | F28: =AVERAGEIF('Employee Database'!C3:C502,B28,'Employee Database'!N3:N502) -> 3.7635417
B29: Finance | C29: =COUNTIF('Employee Database'!C3:C502,"Finance") -> 53 | D29: =AVERAGEIF('Employee Database'!C3:C502,B29,'Employee Database'!I3:I502) -> 158641.51 | E29: =SUMIF('Employee Database'!C3:C502,B29,'Employee Database'!L3:L502) -> 9920981 | F29: =AVERAGEIF('Employee Database'!C3:C502,B29,'Employee Database'!N3:N502) -> 3.7984906
B30: Operations | C30: =COUNTIF('Employee Database'!C3:C502,"Operations") -> 52 | D30: =AVERAGEIF('Employee Database'!C3:C502,B30,'Employee Database'!I3:I502) -> 135192.31 | E30: =SUMIF('Employee Database'!C3:C502,B30,'Employee Database'!L3:L502) -> 8318940 | F30: =AVERAGEIF('Employee Database'!C3:C502,B30,'Employee Database'!N3:N502) -> 3.5315385
B31: Legal | C31: =COUNTIF('Employee Database'!C3:C502,"Legal") -> 57 | D31: =AVERAGEIF('Employee Database'!C3:C502,B31,'Employee Database'!I3:I502) -> 136245.61 | E31: =SUMIF('Employee Database'!C3:C502,B31,'Employee Database'!L3:L502) -> 9178731 | F31: =AVERAGEIF('Employee Database'!C3:C502,B31,'Employee Database'!N3:N502) -> 3.6177193
B32: Product | C32: =COUNTIF('Employee Database'!C3:C502,"Product") -> 57 | D32: =AVERAGEIF('Employee Database'!C3:C502,B32,'Employee Database'!I3:I502) -> 144894.74 | E32: =SUMIF('Employee Database'!C3:C502,B32,'Employee Database'!L3:L502) -> 9903822 | F32: =AVERAGEIF('Employee Database'!C3:C502,B32,'Employee Database'!N3:N502) -> 3.7624561
B33: Design | C33: =COUNTIF('Employee Database'!C3:C502,"Design") -> 43 | D33: =AVERAGEIF('Employee Database'!C3:C502,B33,'Employee Database'!I3:I502) -> 140860.47 | E33: =SUMIF('Employee Database'!C3:C502,B33,'Employee Database'!L3:L502) -> 7213240 | F33: =AVERAGEIF('Employee Database'!C3:C502,B33,'Employee Database'!N3:N502) -> 3.7704651
B34: Support | C34: =COUNTIF('Employee Database'!C3:C502,"Support") -> 52 | D34: =AVERAGEIF('Employee Database'!C3:C502,B34,'Employee Database'!I3:I502) -> 128961.54 | E34: =SUMIF('Employee Database'!C3:C502,B34,'Employee Database'!L3:L502) -> 7920533 | F34: =AVERAGEIF('Employee Database'!C3:C502,B34,'Employee Database'!N3:N502) -> 3.7242308

Sheet Employee Database
A1: 🏢 Employee Database — FY 2024–25
A2: Emp ID | B2: Full Name | C2: Department | D2: Job Grade | E2: Location | F2: Gender | G2: Date of Birth | H2: Join Date | I2: Base Salary (NPR) | J2: Bonus % | K2: Annual Bonus (NPR) | L2: Total Comp (NPR) | M2: Experience (Yrs) | N2: Performance Score | O2: Attendance % | P2: Projects Done | Q2: Training Hours | R2: Email | S2: Phone | T2: Status
A3: EMP0001 | B3: Daniel Doyle | C3: Sales | D3: Junior | E3: Butwal | F3: Male | G3: 33261 | H3: 38531 | I3: 83000 | J3: 0.085 | K3: =J3*I3 -> 7055 | L3: =I3+K3 -> 90055 | M3: 19.5 | N3: 2.76 | O3: 0.922 | P3: 35 | Q3: 32 | R3: garzaanthony@example.org | S3: 538.990.8386 | T3: On Leave
A4: EMP0002 | B4: Robert Wolfe | C4: Legal | D4: Junior | E4: Kathmandu | F4: Male | G4: 32583 | H4: 44116 | I4: 82000 | J4: 0.108 | K4: =J4*I4 -> 8856 | L4: =I4+K4 -> 90856 | M4: 4.2 | N4: 4.01 | O4: 0.868 | P4: 35 | Q4: 117 | R4: joshua35@example.org | S4: 361-855-9407 | T4: Active
A5: EMP0003 | B5: Stacey Ward | C5: Product | D5: Manager | E5: Butwal | F5: Male | G5: 25684 | H5: 40440 | I5: 223000 | J5: 0.251 | K5: =J5*I5 -> 55973 | L5: =I5+K5 -> 278973 | M5: 14.3 | N5: 4.25 | O5: 0.802 | P5: 10 | Q5: 65 | R5: janetwilliams@example.org | S5: 001-341-431-64 | T5: Active
A6: EMP0004 | B6: Devin Schaefer | C6: Sales | D6: Junior | E6: Hetauda | F6: Male | G6: 31838 | H6: 40096 | I6: 119000 | J6: 0.262 | K6: =J6*I6 -> 31178 | L6: =I6+K6 -> 150178 | M6: 15.2 | N6: 4.01 | O6: 0.942 | P6: 30 | Q6: 147 | R6: gabriellecameron@example.org | S6: 505.964.1395 | T6: Active
A7: EMP0005 | B7: Derek Wright | C7: Legal | D7: Junior | E7: Butwal | F7: Other | G7: 29966 | H7: 44864 | I7: 187000 | J7: 0.271 | K7: =J7*I7 -> 50677 | L7: =I7+K7 -> 237677 | M7: 2.2 | N7: 3.4 | O7: 0.758 | P7: 5 | Q7: 21 | R7: julie69@example.com | S7: (332)887-1012x | T7: Resigned
A8: EMP0006 | B8: Tricia Valencia | C8: HR | D8: VP | E8: Butwal | F8: Male | G8: 29777 | H8: 45445 | I8: 249000 | J8: 0.108 | K8: =J8*I8 -> 26892 | L8: =I8+K8 -> 275892 | M8: 0.6 | N8: 2.75 | O8: 0.783 | P8: 24 | Q8: 51 | R8: frazierdanny@example.net | S8: 001-645-514-62 | T8: Active
A9: EMP0007 | B9: Paula Moreno | C9: Operations | D9: Mid | E9: Butwal | F9: Other | G9: 26685 | H9: 43782 | I9: 204000 | J9: 0.212 | K9: =J9*I9 -> 43248 | L9: =I9+K9 -> 247248 | M9: 5.1 | N9: 4.02 | O9: 0.751 | P9: 16 | Q9: 51 | R9: georgetracy@example.org | S9: (443)903-9117x | T9: Active
A10: EMP0008 | B10: Lisa Brandt | C10: Legal | D10: Senior | E10: Biratnagar | F10: Other | G10: 37416 | H10: 39528 | I10: 110000 | J10: 0.261 | K10: =J10*I10 -> 28710 | L10: =I10+K10 -> 138710 | M10: 16.8 | N10: 4.44 | O10: 0.769 | P10: 3 | Q10: 90 | R10: jenniferross@example.net | S10: +1-557-587-133 | T10: Active
A11: EMP0009 | B11: Austin Johnson | C11: Finance | D11: Junior | E11: Biratnagar | F11: Other | G11: 24717 | H11: 43392 | I11: 213000 | J11: 0.129 | K11: =J11*I11 -> 27477 | L11: =I11+K11 -> 240477 | M11: 6.2 | N11: 4.14 | O11: 0.819 | P11: 30 | Q11: 46 | R11: chad34@example.net | S11: 838.729.9737x6 | T11: Active
A12: EMP0010 | B12: Megan Joyce | C12: Marketing | D12: Mid | E12: Butwal | F12: Other | G12: 30344 | H12: 41678 | I12: 178000 | J12: 0.157 | K12: =J12*I12 -> 27946 | L12: =I12+K12 -> 205946 | M12: 10.9 | N12: 3.96 | O12: 0.809 | P12: 9 | Q12: 140 | R12: brownjessica@example.org | S12: 933.587.2624 | T12: Active
A13: EMP0011 | B13: Savannah Garcia | C13: Sales | D13: VP | E13: Kathmandu | F13: Male | G13: 36438 | H13: 38889 | I13: 65000 | J13: 0.207 | K13: =J13*I13 -> 13455 | L13: =I13+K13 -> 78455 | M13: 18.5 | N13: 4.48 | O13: 0.827 | P13: 5 | Q13: 108 | R13: novaksara@example.org | S13: (267)873-6026 | T13: Active
A14: EMP0012 | B14: Jay Bernard | C14: Support | D14: Lead | E14: Butwal | F14: Other | G14: 28204 | H14: 43935 | I14: 28000 | J14: 0.22 | K14: =J14*I14 -> 6160 | L14: =I14+K14 -> 34160 | M14: 4.7 | N14: 2.79 | O14: 0.965 | P14: 18 | Q14: 174 | R14: smoore@example.org | S14: 4982050097 | T14: Active
... A502: EMP0500 | B502: Brandy Jacobson | C502: HR | D502: Lead | E502: Hetauda | F502: Female | G502: 31597 | H502: 42354 | I502: 90000 | J502: 0.091 | K502: =J502*I502 -> 8190 | L502: =I502+K502 -> 98190 | M502: 9 | N502: 4.34 | O502: 0.817 | P502: 25 | Q502: 66 | R502: kevincollins@example.org | S502: 393.911.0291x8 | T502: Active
A503: TOTALS / AVERAGES | I503: =AVERAGE(I3:I502) -> 140280 | K503: =SUM(K3:K502) -> 12699263 | L503: =SUM(L3:L502) -> 82839263 | M503: =AVERAGE(M3:M502) -> 10.5136 | N503: =AVERAGE(N3:N502) -> 3.69766 | O503: =AVERAGE(O3:O502) -> 0.860214 | P503: =SUM(P3:P502) -> 10301 | Q503: =SUM(Q3:Q502) -> 52772

Sheet Monthly Sales
A1: 📊 Monthly Sales Report — 2022 to 2024
A2: Sale ID | B2: Month | C2: Year | D2: Product | E2: Category | F2: Region | G2: Channel | H2: Units Sold | I2: Unit Price (NPR) | J2: Revenue (NPR) | K2: COGS (NPR) | L2: Gross Profit (NPR) | M2: Gross Margin % | N2: Discount % | O2: Net Revenue (NPR) | P2: Returns | Q2: Return Rate % | R2: Rep Name | S2: Quarter | T2: Target Met?
A3: SL00001 | B3: Feb | C3: 2023 | D3: Drawing Tablet | E3: Input | F3: Gandaki | G3: Government | H3: 392 | I3: 2999 | J3: =H3*I3 -> 1175608 | K3: =J3*0.68 -> 799413.44 | L3: =J3-K3 -> 376194.56 | M3: =IF(J3=0,0,L3/J3) -> 0.32 | N3: 0.12 | O3: =J3*(1-N3) -> 1034535 | P3: 8 | Q3: =IF(H3=0,0,P3/H3) -> 0.020408163 | R3: Jonathan Myers | S3: Q1 | T3: Yes
A4: SL00002 | B4: Nov | C4: 2024 | D4: Cooling Pad | E4: Accessories | F4: Karnali | G4: Wholesale | H4: 212 | I4: 2499 | J4: =H4*I4 -> 529788 | K4: =J4*0.66 -> 349660.08 | L4: =J4-K4 -> 180127.92 | M4: =IF(J4=0,0,L4/J4) -> 0.34 | N4: 0.03 | O4: =J4*(1-N4) -> 513894.36 | P4: 4 | Q4: =IF(H4=0,0,P4/H4) -> 0.018867925 | R4: Elizabeth Webb | S4: Q4 | T4: Yes
A5: SL00003 | B5: Nov | C5: 2023 | D5: Smart Headset | E5: Audio | F5: Lumbini | G5: Wholesale | H5: 359 | I5: 11999 | J5: =H5*I5 -> 4307641 | K5: =J5*0.57 -> 2455355.4 | L5: =J5-K5 -> 1852285.6 | M5: =IF(J5=0,0,L5/J5) -> 0.43 | N5: 0.05 | O5: =J5*(1-N5) -> 4092259 | P5: 4 | Q5: =IF(H5=0,0,P5/H5) -> 0.011142061 | R5: David Abbott | S5: Q4 | T5: Yes
A6: SL00004 | B6: Sep | C6: 2022 | D6: USB-C Hub | E6: Accessories | F6: Bagmati | G6: Wholesale | H6: 138 | I6: 12999 | J6: =H6*I6 -> 1793862 | K6: =J6*0.63 -> 1130133.1 | L6: =J6-K6 -> 663728.94 | M6: =IF(J6=0,0,L6/J6) -> 0.37 | N6: 0.11 | O6: =J6*(1-N6) -> 1596537.2 | P6: 1 | Q6: =IF(H6=0,0,P6/H6) -> 0.0072463768 | R6: Lonnie Gonzales | S6: Q3 | T6: Yes
A7: SL00005 | B7: Mar | C7: 2022 | D7: RAM 16GB | E7: Memory | F7: Gandaki | G7: Wholesale | H7: 216 | I7: 35999 | J7: =H7*I7 -> 7775784 | K7: =J7*0.65 -> 5054259.6 | L7: =J7-K7 -> 2721524.4 | M7: =IF(J7=0,0,L7/J7) -> 0.35 | N7: 0.07 | O7: =J7*(1-N7) -> 7231479.1 | P7: 5 | Q7: =IF(H7=0,0,P7/H7) -> 0.023148148 | R7: Barbara Thomas | S7: Q1 | T7: No
A8: SL00006 | B8: Dec | C8: 2022 | D8: Webcam HD | E8: Peripherals | F8: Bagmati | G8: Retail Store | H8: 29 | I8: 35999 | J8: =H8*I8 -> 1043971 | K8: =J8*0.64 -> 668141.44 | L8: =J8-K8 -> 375829.56 | M8: =IF(J8=0,0,L8/J8) -> 0.36 | N8: 0.01 | O8: =J8*(1-N8) -> 1033531.3 | P8: 1 | Q8: =IF(H8=0,0,P8/H8) -> 0.034482759 | R8: Charles Garner | S8: Q4 | T8: Yes
A9: SL00007 | B9: Apr | C9: 2023 | D9: Cable Organiser | E9: Accessories | F9: Lumbini | G9: Online | H9: 63 | I9: 2999 | J9: =H9*I9 -> 188937 | K9: =J9*0.63 -> 119030.31 | L9: =J9-K9 -> 69906.69 | M9: =IF(J9=0,0,L9/J9) -> 0.37 | N9: 0.06 | O9: =J9*(1-N9) -> 177600.78 | P9: 3 | Q9: =IF(H9=0,0,P9/H9) -> 0.047619048 | R9: Jorge Lyons | S9: Q2 | T9: Yes
A10: SL00008 | B10: Dec | C10: 2022 | D10: Mechanical Keyboard | E10: Peripherals | F10: Lumbini | G10: Online | H10: 267 | I10: 24999 | J10: =H10*I10 -> 6674733 | K10: =J10*0.7 -> 4672313.1 | L10: =J10-K10 -> 2002419.9 | M10: =IF(J10=0,0,L10/J10) -> 0.3 | N10: 0.07 | O10: =J10*(1-N10) -> 6207501.7 | P10: 10 | Q10: =IF(H10=0,0,P10/H10) -> 0.037453184 | R10: John Roberts | S10: Q4 | T10: Yes
A11: SL00009 | B11: Jun | C11: 2022 | D11: Drawing Tablet | E11: Input | F11: Sudurpashchim | G11: Online | H11: 382 | I11: 299 | J11: =H11*I11 -> 114218 | K11: =J11*0.59 -> 67388.62 | L11: =J11-K11 -> 46829.38 | M11: =IF(J11=0,0,L11/J11) -> 0.41 | N11: 0.02 | O11: =J11*(1-N11) -> 111933.64 | P11: 15 | Q11: =IF(H11=0,0,P11/H11) -> 0.039267016 | R11: Kevin Richardson | S11: Q2 | T11: Yes
A12: SL00010 | B12: Apr | C12: 2023 | D12: Screen Cleaner | E12: Accessories | F12: Bagmati | G12: Retail Store | H12: 499 | I12: 7999 | J12: =H12*I12 -> 3991501 | K12: =J12*0.51 -> 2035665.5 | L12: =J12-K12 -> 1955835.5 | M12: =IF(J12=0,0,L12/J12) -> 0.49 | N12: 0.07 | O12: =J12*(1-N12) -> 3712095.9 | P12: 0 | Q12: =IF(H12=0,0,P12/H12) -> 0 | R12: James Marsh | S12: Q2 | T12: Yes
A13: SL00011 | B13: May | C13: 2024 | D13: Wireless Mouse | E13: Peripherals | F13: Lumbini | G13: Retail Store | H13: 5 | I13: 4999 | J13: =H13*I13 -> 24995 | K13: =J13*0.6 -> 14997 | L13: =J13-K13 -> 9998 | M13: =IF(J13=0,0,L13/J13) -> 0.4 | N13: 0.1 | O13: =J13*(1-N13) -> 22495.5 | P13: 0 | Q13: =IF(H13=0,0,P13/H13) -> 0 | R13: Robert Hernandez | S13: Q2 | T13: Yes
A14: SL00012 | B14: Feb | C14: 2022 | D14: USB-C Hub | E14: Accessories | F14: Lumbini | G14: Online | H14: 352 | I14: 11999 | J14: =H14*I14 -> 4223648 | K14: =J14*0.53 -> 2238533.4 | L14: =J14-K14 -> 1985114.6 | M14: =IF(J14=0,0,L14/J14) -> 0.47 | N14: 0.15 | O14: =J14*(1-N14) -> 3590100.8 | P14: 1 | Q14: =IF(H14=0,0,P14/H14) -> 0.0028409091 | R14: Bryan Price | S14: Q1 | T14: Yes
A15: SL00013 | B15: Jun | C15: 2024 | D15: USB-C Hub | E15: Accessories | F15: Sudurpashchim | G15: Government | H15: 406 | I15: 7999 | J15: =H15*I15 -> 3247594 | K15: =J15*0.48 -> 1558845.1 | L15: =J15-K15 -> 1688748.9 | M15: =IF(J15=0,0,L15/J15) -> 0.52 | N15: 0.03 | O15: =J15*(1-N15) -> 3150166.2 | P15: 17 | Q15: =IF(H15=0,0,P15/H15) -> 0.041871921 | R15: Amanda Santos | S15: Q2 | T15: Yes
A16: SL00014 | B16: Aug | C16: 2024 | D16: Mechanical Keyboard | E16: Peripherals | F16: Bagmati | G16: Corporate | H16: 184 | I16: 3999 | J16: =H16*I16 -> 735816 | K16: =J16*0.48 -> 353191.68 | L16: =J16-K16 -> 382624.32 | M16: =IF(J16=0,0,L16/J16) -> 0.52 | N16: 0.13 | O16: =J16*(1-N16) -> 640159.92 | P16: 7 | Q16: =IF(H16=0,0,P16/H16) -> 0.038043478 | R16: Jill Odonnell | S16: Q3 | T16: No
A17: SL00015 | B17: Sep | C17: 2023 | D17: Cooling Pad | E17: Accessories | F17: Sudurpashchim | G17: Corporate | H17: 98 | I17: 11999 | J17: =H17*I17 -> 1175902 | K17: =J17*0.5 -> 587951 | L17: =J17-K17 -> 587951 | M17: =IF(J17=0,0,L17/J17) -> 0.5 | N17: 0.05 | O17: =J17*(1-N17) -> 1117106.9 | P17: 3 | Q17: =IF(H17=0,0,P17/H17) -> 0.030612245 | R17: Charles Khan | S17: Q3 | T17: Yes
A18: SL00016 | B18: Oct | C18: 2024 | D18: USB-C Hub | E18: Accessories | F18: Bagmati | G18: Government | H18: 80 | I18: 9999 | J18: =H18*I18 -> 799920 | K18: =J18*0.52 -> 415958.4 | L18: =J18-K18 -> 383961.6 | M18: =IF(J18=0,0,L18/J18) -> 0.48 | N18: 0.04 | O18: =J18*(1-N18) -> 767923.2 | P18: 2 | Q18: =IF(H18=0,0,P18/H18) -> 0.025 | R18: Adam Moore | S18: Q4 | T18: No
A19: SL00017 | B19: Jan | C19: 2024 | D19: Cooling Pad | E19: Accessories | F19: Lumbini | G19: Retail Store | H19: 453 | I19: 4999 | J19: =H19*I19 -> 2264547 | K19: =J19*0.6 -> 1358728.2 | L19: =J19-K19 -> 905818.8 | M19: =IF(J19=0,0,L19/J19) -> 0.4 | N19: 0.05 | O19: =J19*(1-N19) -> 2151319.6 | P19: 19 | Q19: =IF(H19=0,0,P19/H19) -> 0.041942605 | R19: Shannon Clark | S19: Q1 | T19: Yes
A20: SL00018 | B20: Jun | C20: 2024 | D20: Wireless Mouse | E20: Peripherals | F20: Sudurpashchim | G20: Government | H20: 420 | I20: 15999 | J20: =H20*I20 -> 6719580 | K20: =J20*0.5 -> 3359790 | L20: =J20-K20 -> 3359790 | M20: =IF(J20=0,0,L20/J20) -> 0.5 | N20: 0.1 | O20: =J20*(1-N20) -> 6047622 | P20: 17 | Q20: =IF(H20=0,0,P20/H20) -> 0.04047619 | R20: Kelly Palmer | S20: Q2 | T20: Yes
A21: SL00019 | B21: Oct | C21: 2023 | D21: Webcam HD | E21: Peripherals | F21: Lumbini | G21: Wholesale | H21: 57 | I21: 7999 | J21: =H21*I21 -> 455943 | K21: =J21*0.58 -> 264446.94 | L21: =J21-K21 -> 191496.06 | M21: =IF(J21=0,0,L21/J21) -> 0.42 | N21: 0.01 | O21: =J21*(1-N21) -> 451383.57 | P21: 0 | Q21: =IF(H21=0,0,P21/H21) -> 0 | R21: Christian Rios | S21: Q4 | T21: Yes
A22: SL00020 | B22: Jan | C22: 2022 | D22: Wireless Mouse | E22: Peripherals | F22: Lumbini | G22: Retail Store | H22: 51 | I22: 4999 | J22: =H22*I22 -> 254949 | K22: =J22*0.59 -> 150419.91 | L22: =J22-K22 -> 104529.09 | M22: =IF(J22=0,0,L22/J22) -> 0.41 | N22: 0.13 | O22: =J22*(1-N22) -> 221805.63 | P22: 2 | Q22: =IF(H22=0,0,P22/H22) -> 0.039215686 | R22: Julia Trevino | S22: Q1 | T22: No
A23: SL00021 | B23: Sep | C23: 2024 | D23: Portable Charger | E23: Accessories | F23: Madhesh | G23: Wholesale | H23: 26 | I23: 8999 | J23: =H23*I23 -> 233974 | K23: =J23*0.51 -> 119326.74 | L23: =J23-K23 -> 114647.26 | M23: =IF(J23=0,0,L23/J23) -> 0.49 | N23: 0.11 | O23: =J23*(1-N23) -> 208236.86 | P23: 0 | Q23: =IF(H23=0,0,P23/H23) -> 0 | R23: Richard Barrett | S23: Q3 | T23: Yes
A24: SL00022 | B24: Nov | C24: 2023 | D24: Screen Cleaner | E24: Accessories | F24: Karnali | G24: Online | H24: 240 | I24: 2999 | J24: =H24*I24 -> 719760 | K24: =J24*0.61 -> 439053.6 | L24: =J24-K24 -> 280706.4 | M24: =IF(J24=0,0,L24/J24) -> 0.39 | N24: 0.05 | O24: =J24*(1-N24) -> 683772 | P24: 11 | Q24: =IF(H24=0,0,P24/H24) -> 0.045833333 | R24: Andrea Franco | S24: Q4 | T24: No
A25: SL00023 | B25: Jun | C25: 2024 | D25: Laptop Pro X | E25: Computing | F25: Karnali | G25: Government | H25: 137 | I25: 1999 | J25: =H25*I25 -> 273863 | K25: =J25*0.46 -> 125976.98 | L25: =J25-K25 -> 147886.02 | M25: =IF(J25=0,0,L25/J25) -> 0.54 | N25: 0.01 | O25: =J25*(1-N25) -> 271124.37 | P25: 2 | Q25: =IF(H25=0,0,P25/H25) -> 0.01459854 | R25: Dr. Larry White | S25: Q2 | T25: Yes
A26: SL00024 | B26: Apr | C26: 2024 | D26: Wireless Mouse | E26: Peripherals | F26: Bagmati | G26: Retail Store | H26: 273 | I26: 15999 | J26: =H26*I26 -> 4367727 | K26: =J26*0.5 -> 2183863.5 | L26: =J26-K26 -> 2183863.5 | M26: =IF(J26=0,0,L26/J26) -> 0.5 | N26: 0.08 | O26: =J26*(1-N26) -> 4018308.8 | P26: 3 | Q26: =IF(H26=0,0,P26/H26) -> 0.010989011 | R26: Katie Hopkins | S26: Q2 | T26: Yes
A27: SL00025 | B27: Sep | C27: 2024 | D27: Cooling Pad | E27: Accessories | F27: Lumbini | G27: Online | H27: 393 | I27: 24999 | J27: =H27*I27 -> 9824607 | K27: =J27*0.59 -> 5796518.1 | L27: =J27-K27 -> 4028088.9 | M27: =IF(J27=0,0,L27/J27) -> 0.41 | N27: 0.1 | O27: =J27*(1-N27) -> 8842146.3 | P27: 13 | Q27: =IF(H27=0,0,P27/H27) -> 0.03307888 | R27: Michael Chapman | S27: Q3 | T27: Yes
A28: SL00026 | B28: Mar | C28: 2022 | D28: Cooling Pad | E28: Accessories | F28: Lumbini | G28: Government | H28: 173 | I28: 24999 | J28: =H28*I28 -> 4324827 | K28: =J28*0.49 -> 2119165.2 | L28: =J28-K28 -> 2205661.8 | M28: =IF(J28=0,0,L28/J28) -> 0.51 | N28: 0.15 | O28: =J28*(1-N28) -> 3676103 | P28: 7 | Q28: =IF(H28=0,0,P28/H28) -> 0.040462428 | R28: Lauren Gallegos | S28: Q1 | T28: Yes
A29: SL00027 | B29: Jun | C29: 2024 | D29: Webcam HD | E29: Peripherals | F29: Karnali | G29: Wholesale | H29: 212 | I29: 2999 | J29: =H29*I29 -> 635788 | K29: =J29*0.61 -> 387830.68 | L29: =J29-K29 -> 247957.32 | M29: =IF(J29=0,0,L29/J29) -> 0.39 | N29: 0.12 | O29: =J29*(1-N29) -> 559493.44 | P29: 5 | Q29: =IF(H29=0,0,P29/H29) -> 0.023584906 | R29: Allen Quinn | S29: Q2 | T29: Yes
A30: SL00028 | B30: Oct | C30: 2024 | D30: Mechanical Keyboard | E30: Peripherals | F30: Lumbini | G30: Government | H30: 475 | I30: 3999 | J30: =H30*I30 -> 1899525 | K30: =J30*0.51 -> 968757.75 | L30: =J30-K30 -> 930767.25 | M30: =IF(J30=0,0,L30/J30) -> 0.49 | N30: 0.14 | O30: =J30*(1-N30) -> 1633591.5 | P30: 14 | Q30: =IF(H30=0,0,P30/H30) -> 0.029473684 | R30: Maurice Porter | S30: Q4 | T30: No
A31: SL00029 | B31: Jan | C31: 2024 | D31: Laptop Pro X | E31: Computing | F31: Koshi | G31: Government | H31: 9 | I31: 1999 | J31: =H31*I31 -> 17991 | K31: =J31*0.48 -> 8635.68 | L31: =J31-K31 -> 9355.32 | M31: =IF(J31=0,0,L31/J31) -> 0.52 | N31: 0.13 | O31: =J31*(1-N31) -> 15652.17 | P31: 0 | Q31: =IF(H31=0,0,P31/H31) -> 0 | R31: Erica Hall | S31: Q1 | T31: Yes
A32: SL00030 | B32: Apr | C32: 2022 | D32: Cable Organiser | E32: Accessories | F32: Koshi | G32: Online | H32: 396 | I32: 799 | J32: =H32*I32 -> 316404 | K32: =J32*0.69 -> 218318.76 | L32: =J32-K32 -> 98085.24 | M32: =IF(J32=0,0,L32/J32) -> 0.31 | N32: 0.12 | O32: =J32*(1-N32) -> 278435.52 | P32: 17 | Q32: =IF(H32=0,0,P32/H32) -> 0.042929293 | R32: Sylvia Flynn | S32: Q2 | T32: Yes
A33: SL00031 | B33: Feb | C33: 2022 | D33: RAM 16GB | E33: Memory | F33: Koshi | G33: Retail Store | H33: 71 | I33: 35999 | J33: =H33*I33 -> 2555929 | K33: =J33*0.54 -> 1380201.7 | L33: =J33-K33 -> 1175727.3 | M33: =IF(J33=0,0,L33/J33) -> 0.46 | N33: 0.09 | O33: =J33*(1-N33) -> 2325895.4 | P33: 1 | Q33: =IF(H33=0,0,P33/H33) -> 0.014084507 | R33: Spencer Chandler | S33: Q1 | T33: Yes
A34: SL00032 | B34: May | C34: 2022 | D34: Smart Headset | E34: Audio | F34: Lumbini | G34: Government | H34: 470 | I34: 2499 | J34: =H34*I34 -> 1174530 | K34: =J34*0.63 -> 739953.9 | L34: =J34-K34 -> 434576.1 | M34: =IF(J34=0,0,L34/J34) -> 0.37 | N34: 0.11 | O34: =J34*(1-N34) -> 1045331.7 | P34: 15 | Q34: =IF(H34=0,0,P34/H34) -> 0.031914894 | R34: William Nielsen | S34: Q2 | T34: Yes
A35: SL00033 | B35: Aug | C35: 2024 | D35: Portable Charger | E35: Accessories | F35: Madhesh | G35: Online | H35: 305 | I35: 24999 | J35: =H35*I35 -> 7624695 | K35: =J35*0.53 -> 4041088.4 | L35: =J35-K35 -> 3583606.6 | M35: =IF(J35=0,0,L35/J35) -> 0.47 | N35: 0.11 | O35: =J35*(1-N35) -> 6785978.5 | P35: 12 | Q35: =IF(H35=0,0,P35/H35) -> 0.039344262 | R35: David Johnson | S35: Q3 | T35: Yes
A36: SL00034 | B36: Jan | C36: 2023 | D36: Webcam HD | E36: Peripherals | F36: Karnali | G36: Corporate | H36: 214 | I36: 299 | J36: =H36*I36 -> 63986 | K36: =J36*0.67 -> 42870.62 | L36: =J36-K36 -> 21115.38 | M36: =IF(J36=0,0,L36/J36) -> 0.33 | N36: 0.13 | O36: =J36*(1-N36) -> 55667.82 | P36: 3 | Q36: =IF(H36=0,0,P36/H36) -> 0.014018692 | R36: Jessica Brooks | S36: Q1 | T36: Yes
A37: SL00035 | B37: Nov | C37: 2024 | D37: SSD 1TB | E37: Storage | F37: Bagmati | G37: Wholesale | H37: 269 | I37: 4999 | J37: =H37*I37 -> 1344731 | K37: =J37*0.53 -> 712707.43 | L37: =J37-K37 -> 632023.57 | M37: =IF(J37=0,0,L37/J37) -> 0.47 | N37: 0.08 | O37: =J37*(1-N37) -> 1237152.5 | P37: 5 | Q37: =IF(H37=0,0,P37/H37) -> 0.018587361 | R37: Alyssa Thompson | S37: Q4 | T37: Yes
A38: SL00036 | B38: Mar | C38: 2022 | D38: Drawing Tablet | E38: Input | F38: Sudurpashchim | G38: Corporate | H38: 498 | I38: 9999 | J38: =H38*I38 -> 4979502 | K38: =J38*0.64 -> 3186881.3 | L38: =J38-K38 -> 1792620.7 | M38: =IF(J38=0,0,L38/J38) -> 0.36 | N38: 0.09 | O38: =J38*(1-N38) -> 4531346.8 | P38: 2 | Q38: =IF(H38=0,0,P38/H38) -> 0.0040160643 | R38: Jerry Anderson | S38: Q1 | T38: Yes
A39: SL00037 | B39: Jul | C39: 2023 | D39: LED Desk Lamp | E39: Accessories | F39: Lumbini | G39: Retail Store | H39: 68 | I39: 8999 | J39: =H39*I39 -> 611932 | K39: =J39*0.47 -> 287608.04 | L39: =J39-K39 -> 324323.96 | M39: =IF(J39=0,0,L39/J39) -> 0.53 | N39: 0.09 | O39: =J39*(1-N39) -> 556858.12 | P39: 0 | Q39: =IF(H39=0,0,P39/H39) -> 0 | R39: Kristie Gonzalez | S39: Q3 | T39: No
A40: SL00038 | B40: May | C40: 2022 | D40: SSD 1TB | E40: Storage | F40: Madhesh | G40: Corporate | H40: 397 | I40: 3999 | J40: =H40*I40 -> 1587603 | K40: =J40*0.48 -> 762049.44 | L40: =J40-K40 -> 825553.56 | M40: =IF(J40=0,0,L40/J40) -> 0.52 | N40: 0.02 | O40: =J40*(1-N40) -> 1555850.9 | P40: 17 | Q40: =IF(H40=0,0,P40/H40) -> 0.042821159 | R40: Michael Perez DDS | S40: Q2 | T40: Yes
A41: SL00039 | B41: Aug | C41: 2023 | D41: Drawing Tablet | E41: Input | F41: Madhesh | G41: Retail Store | H41: 288 | I41: 11999 | J41: =H41*I41 -> 3455712 | K41: =J41*0.7 -> 2418998.4 | L41: =J41-K41 -> 1036713.6 | M41: =IF(J41=0,0,L41/J41) -> 0.3 | N41: 0.08 | O41: =J41*(1-N41) -> 3179255 | P41: 3 | Q41: =IF(H41=0,0,P41/H41) -> 0.010416667 | R41: Joseph Tyler | S41: Q3 | T41: Yes
A42: SL00040 | B42: May | C42: 2023 | D42: Webcam HD | E42: Peripherals | F42: Sudurpashchim | G42: Government | H42: 46 | I42: 7999 | J42: =H42*I42 -> 367954 | K42: =J42*0.62 -> 228131.48 | L42: =J42-K42 -> 139822.52 | M42: =IF(J42=0,0,L42/J42) -> 0.38 | N42: 0.06 | O42: =J42*(1-N42) -> 345876.76 | P42: 1 | Q42: =IF(H42=0,0,P42/H42) -> 0.02173913 | R42: Alexander Moyer | S42: Q2 | T42: Yes
A43: SL00041 | B43: Jun | C43: 2023 | D43: Smart Headset | E43: Audio | F43: Sudurpashchim | G43: Online | H43: 395 | I43: 35999 | J43: =H43*I43 -> 14219605 | K43: =J43*0.49 -> 6967606.5 | L43: =J43-K43 -> 7251998.5 | M43: =IF(J43=0,0,L43/J43) -> 0.51 | N43: 0.05 | O43: =J43*(1-N43) -> 13508625 | P43: 14 | Q43: =IF(H43=0,0,P43/H43) -> 0.035443038 | R43: Andrew Taylor | S43: Q2 | T43: Yes
A44: SL00042 | B44: Aug | C44: 2022 | D44: Screen Cleaner | E44: Accessories | F44: Karnali | G44: Retail Store | H44: 103 | I44: 24999 | J44: =H44*I44 -> 2574897 | K44: =J44*0.54 -> 1390444.4 | L44: =J44-K44 -> 1184452.6 | M44: =IF(J44=0,0,L44/J44) -> 0.46 | N44: 0.11 | O44: =J44*(1-N44) -> 2291658.3 | P44: 0 | Q44: =IF(H44=0,0,P44/H44) -> 0 | R44: Raymond Carroll | S44: Q3 | T44: Yes
A45: SL00043 | B45: Dec | C45: 2022 | D45: Mechanical Keyboard | E45: Peripherals | F45: Madhesh | G45: Retail Store | H45: 445 | I45: 799 | J45: =H45*I45 -> 355555 | K45: =J45*0.66 -> 234666.3 | L45: =J45-K45 -> 120888.7 | M45: =IF(J45=0,0,L45/J45) -> 0.34 | N45: 0 | O45: =J45*(1-N45) -> 355555 | P45: 22 | Q45: =IF(H45=0,0,P45/H45) -> 0.049438202 | R45: Gina Fleming | S45: Q4 | T45: Yes
A46: SL00044 | B46: May | C46: 2023 | D46: RAM 16GB | E46: Memory | F46: Bagmati | G46: Wholesale | H46: 108 | I46: 3999 | J46: =H46*I46 -> 431892 | K46: =J46*0.58 -> 250497.36 | L46: =J46-K46 -> 181394.64 | M46: =IF(J46=0,0,L46/J46) -> 0.42 | N46: 0.03 | O46: =J46*(1-N46) -> 418935.24 | P46: 4 | Q46: =IF(H46=0,0,P46/H46) -> 0.037037037 | R46: Monica Rice | S46: Q2 | T46: Yes
A47: SL00045 | B47: Sep | C47: 2023 | D47: Smart Headset | E47: Audio | F47: Sudurpashchim | G47: Retail Store | H47: 356 | I47: 3999 | J47: =H47*I47 -> 1423644 | K47: =J47*0.62 -> 882659.28 | L47: =J47-K47 -> 540984.72 | M47: =IF(J47=0,0,L47/J47) -> 0.38 | N47: 0.06 | O47: =J47*(1-N47) -> 1338225.4 | P47: 16 | Q47: =IF(H47=0,0,P47/H47) -> 0.04494382 | R47: Daniel Carey | S47: Q3 | T47: Yes
A48: SL00046 | B48: May | C48: 2022 | D48: Laptop Pro X | E48: Computing | F48: Koshi | G48: Retail Store | H48: 405 | I48: 3999 | J48: =H48*I48 -> 1619595 | K48: =J48*0.6 -> 971757 | L48: =J48-K48 -> 647838 | M48: =IF(J48=0,0,L48/J48) -> 0.4 | N48: 0.01 | O48: =J48*(1-N48) -> 1603399.1 | P48: 20 | Q48: =IF(H48=0,0,P48/H48) -> 0.049382716 | R48: Heather Yoder | S48: Q2 | T48: Yes
A49: SL00047 | B49: Feb | C49: 2023 | D49: Drawing Tablet | E49: Input | F49: Koshi | G49: Wholesale | H49: 443 | I49: 7999 | J49: =H49*I49 -> 3543557 | K49: =J49*0.45 -> 1594600.6 | L49: =J49-K49 -> 1948956.4 | M49: =IF(J49=0,0,L49/J49) -> 0.55 | N49: 0.13 | O49: =J49*(1-N49) -> 3082894.6 | P49: 20 | Q49: =IF(H49=0,0,P49/H49) -> 0.045146727 | R49: Rebecca Gonzales | S49: Q1 | T49: No
A50: SL00048 | B50: Apr | C50: 2023 | D50: Cooling Pad | E50: Accessories | F50: Sudurpashchim | G50: Online | H50: 463 | I50: 8999 | J50: =H50*I50 -> 4166537 | K50: =J50*0.57 -> 2374926.1 | L50: =J50-K50 -> 1791610.9 | M50: =IF(J50=0,0,L50/J50) -> 0.43 | N50: 0.09 | O50: =J50*(1-N50) -> 3791548.7 | P50: 2 | Q50: =IF(H50=0,0,P50/H50) -> 0.0043196544 | R50: Shelly Carroll | S50: Q2 | T50: Yes
A51: SL00049 | B51: Apr | C51: 2024 | D51: RAM 16GB | E51: Memory | F51: Madhesh | G51: Online | H51: 21 | I51: 2499 | J51: =H51*I51 -> 52479 | K51: =J51*0.68 -> 35685.72 | L51: =J51-K51 -> 16793.28 | M51: =IF(J51=0,0,L51/J51) -> 0.32 | N51: 0.05 | O51: =J51*(1-N51) -> 49855.05 | P51: 1 | Q51: =IF(H51=0,0,P51/H51) -> 0.047619048 | R51: Joseph Garcia | S51: Q2 | T51: No
A52: SL00050 | B52: Dec | C52: 2022 | D52: Laptop Pro X | E52: Computing | F52: Koshi | G52: Wholesale | H52: 182 | I52: 24999 | J52: =H52*I52 -> 4549818 | K52: =J52*0.53 -> 2411403.5 | L52: =J52-K52 -> 2138414.5 | M52: =IF(J52=0,0,L52/J52) -> 0.47 | N52: 0.15 | O52: =J52*(1-N52) -> 3867345.3 | P52: 8 | Q52: =IF(H52=0,0,P52/H52) -> 0.043956044 | R52: Mr. Joshua Johnson PhD | S52: Q4 | T52: Yes
A53: SL00051 | B53: Jan | C53: 2024 | D53: 4K Monitor | E53: Display | F53: Lumbini | G53: Online | H53: 484 | I53: 1999 | J53: =H53*I53 -> 967516 | K53: =J53*0.69 -> 667586.04 | L53: =J53-K53 -> 299929.96 | M53: =IF(J53=0,0,L53/J53) -> 0.31 | N53: 0.03 | O53: =J53*(1-N53) -> 938490.52 | P53: 10 | Q53: =IF(H53=0,0,P53/H53) -> 0.020661157 | R53: Ronald Myers | S53: Q1 | T53: No
A54: SL00052 | B54: Nov | C54: 2022 | D54: Wireless Mouse | E54: Peripherals | F54: Sudurpashchim | G54: Corporate | H54: 267 | I54: 24999 | J54: =H54*I54 -> 6674733 | K54: =J54*0.6 -> 4004839.8 | L54: =J54-K54 -> 2669893.2 | M54: =IF(J54=0,0,L54/J54) -> 0.4 | N54: 0.09 | O54: =J54*(1-N54) -> 6074007 | P54: 3 | Q54: =IF(H54=0,0,P54/H54) -> 0.011235955 | R54: Shane Moore | S54: Q4 | T54: No
A55: SL00053 | B55: Apr | C55: 2024 | D55: USB-C Hub | E55: Accessories | F55: Lumbini | G55: Wholesale | H55: 466 | I55: 11999 | J55: =H55*I55 -> 5591534 | K55: =J55*0.53 -> 2963513 | L55: =J55-K55 -> 2628021 | M55: =IF(J55=0,0,L55/J55) -> 0.47 | N55: 0.08 | O55: =J55*(1-N55) -> 5144211.3 | P55: 6 | Q55: =IF(H55=0,0,P55/H55) -> 0.012875536 | R55: Joseph Allen | S55: Q2 | T55: Yes
A56: SL00054 | B56: Oct | C56: 2024 | D56: Drawing Tablet | E56: Input | F56: Karnali | G56: Retail Store | H56: 442 | I56: 12999 | J56: =H56*I56 -> 5745558 | K56: =J56*0.53 -> 3045145.7 | L56: =J56-K56 -> 2700412.3 | M56: =IF(J56=0,0,L56/J56) -> 0.47 | N56: 0.11 | O56: =J56*(1-N56) -> 5113546.6 | P56: 16 | Q56: =IF(H56=0,0,P56/H56) -> 0.036199095 | R56: Lisa Collins | S56: Q4 | T56: Yes
A57: SL00055 | B57: Jul | C57: 2022 | D57: Drawing Tablet | E57: Input | F57: Madhesh | G57: Retail Store | H57: 163 | I57: 7999 | J57: =H57*I57 -> 1303837 | K57: =J57*0.59 -> 769263.83 | L57: =J57-K57 -> 534573.17 | M57: =IF(J57=0,0,L57/J57) -> 0.41 | N57: 0.14 | O57: =J57*(1-N57) -> 1121299.8 | P57: 1 | Q57: =IF(H57=0,0,P57/H57) -> 0.0061349693 | R57: Kimberly Snow | S57: Q3 | T57: Yes
A58: SL00056 | B58: Jun | C58: 2022 | D58: Portable Charger | E58: Accessories | F58: Bagmati | G58: Wholesale | H58: 451 | I58: 15999 | J58: =H58*I58 -> 7215549 | K58: =J58*0.69 -> 4978728.8 | L58: =J58-K58 -> 2236820.2 | M58: =IF(J58=0,0,L58/J58) -> 0.31 | N58: 0.05 | O58: =J58*(1-N58) -> 6854771.5 | P58: 20 | Q58: =IF(H58=0,0,P58/H58) -> 0.044345898 | R58: Taylor Mercer | S58: Q2 | T58: Yes
A59: SL00057 | B59: Mar | C59: 2022 | D59: Wireless Mouse | E59: Peripherals | F59: Gandaki | G59: Retail Store | H59: 14 | I59: 2999 | J59: =H59*I59 -> 41986 | K59: =J59*0.7 -> 29390.2 | L59: =J59-K59 -> 12595.8 | M59: =IF(J59=0,0,L59/J59) -> 0.3 | N59: 0.09 | O59: =J59*(1-N59) -> 38207.26 | P59: 0 | Q59: =IF(H59=0,0,P59/H59) -> 0 | R59: Amanda Fisher | S59: Q1 | T59: Yes
A60: SL00058 | B60: Apr | C60: 2024 | D60: Laptop Pro X | E60: Computing | F60: Koshi | G60: Online | H60: 353 | I60: 2999 | J60: =H60*I60 -> 1058647 | K60: =J60*0.57 -> 603428.79 | L60: =J60-K60 -> 455218.21 | M60: =IF(J60=0,0,L60/J60) -> 0.43 | N60: 0.08 | O60: =J60*(1-N60) -> 973955.24 | P60: 15 | Q60: =IF(H60=0,0,P60/H60) -> 0.042492918 | R60: Stephen Brown | S60: Q2 | T60: Yes
A61: SL00059 | B61: Mar | C61: 2023 | D61: RAM 16GB | E61: Memory | F61: Lumbini | G61: Retail Store | H61: 84 | I61: 2499 | J61: =H61*I61 -> 209916 | K61: =J61*0.51 -> 107057.16 | L61: =J61-K61 -> 102858.84 | M61: =IF(J61=0,0,L61/J61) -> 0.49 | N61: 0.06 | O61: =J61*(1-N61) -> 197321.04 | P61: 0 | Q61: =IF(H61=0,0,P61/H61) -> 0 | R61: Robert Rivera | S61: Q1 | T61: Yes
A62: SL00060 | B62: Jul | C62: 2022 | D62: Portable Charger | E62: Accessories | F62: Sudurpashchim | G62: Retail Store | H62: 388 | I62: 2499 | J62: =H62*I62 -> 969612 | K62: =J62*0.47 -> 455717.64 | L62: =J62-K62 -> 513894.36 | M62: =IF(J62=0,0,L62/J62) -> 0.53 | N62: 0.14 | O62: =J62*(1-N62) -> 833866.32 | P62: 14 | Q62: =IF(H62=0,0,P62/H62) -> 0.036082474 | R62: Susan Brown | S62: Q3 | T62: No
A63: SL00061 | B63: Dec | C63: 2023 | D63: Cable Organiser | E63: Accessories | F63: Lumbini | G63: Retail Store | H63: 219 | I63: 15999 | J63: =H63*I63 -> 3503781 | K63: =J63*0.64 -> 2242419.8 | L63: =J63-K63 -> 1261361.2 | M63: =IF(J63=0,0,L63/J63) -> 0.36 | N63: 0.09 | O63: =J63*(1-N63) -> 3188440.7 | P63: 6 | Q63: =IF(H63=0,0,P63/H63) -> 0.02739726 | R63: Robert Elliott DDS | S63: Q4 | T63: Yes
A64: SL00062 | B64: Jul | C64: 2024 | D64: Portable Charger | E64: Accessories | F64: Madhesh | G64: Government | H64: 275 | I64: 1999 | J64: =H64*I64 -> 549725 | K64: =J64*0.61 -> 335332.25 | L64: =J64-K64 -> 214392.75 | M64: =IF(J64=0,0,L64/J64) -> 0.39 | N64: 0.11 | O64: =J64*(1-N64) -> 489255.25 | P64: 0 | Q64: =IF(H64=0,0,P64/H64) -> 0 | R64: Rhonda Reed | S64: Q3 | T64: Yes
A65: SL00063 | B65: Aug | C65: 2023 | D65: Cable Organiser | E65: Accessories | F65: Bagmati | G65: Retail Store | H65: 266 | I65: 1999 | J65: =H65*I65 -> 531734 | K65: =J65*0.55 -> 292453.7 | L65: =J65-K65 -> 239280.3 | M65: =IF(J65=0,0,L65/J65) -> 0.45 | N65: 0.11 | O65: =J65*(1-N65) -> 473243.26 | P65: 8 | Q65: =IF(H65=0,0,P65/H65) -> 0.030075188 | R65: Jason Stevenson | S65: Q3 | T65: No
A66: SL00064 | B66: Sep | C66: 2024 | D66: Laptop Pro X | E66: Computing | F66: Gandaki | G66: Wholesale | H66: 226 | I66: 15999 | J66: =H66*I66 -> 3615774 | K66: =J66*0.67 -> 2422568.6 | L66: =J66-K66 -> 1193205.4 | M66: =IF(J66=0,0,L66/J66) -> 0.33 | N66: 0.12 | O66: =J66*(1-N66) -> 3181881.1 | P66: 4 | Q66: =IF(H66=0,0,P66/H66) -> 0.017699115 | R66: Stacy Mendoza | S66: Q3 | T66: No
A67: SL00065 | B67: Mar | C67: 2023 | D67: 4K Monitor | E67: Display | F67: Madhesh | G67: Online | H67: 354 | I67: 1999 | J67: =H67*I67 -> 707646 | K67: =J67*0.68 -> 481199.28 | L67: =J67-K67 -> 226446.72 | M67: =IF(J67=0,0,L67/J67) -> 0.32 | N67: 0.07 | O67: =J67*(1-N67) -> 658110.78 | P67: 14 | Q67: =IF(H67=0,0,P67/H67) -> 0.039548023 | R67: Nathaniel Garcia | S67: Q1 | T67: Yes
A68: SL00066 | B68: Dec | C68: 2024 | D68: Wireless Mouse | E68: Peripherals | F68: Gandaki | G68: Government | H68: 481 | I68: 299 | J68: =H68*I68 -> 143819 | K68: =J68*0.62 -> 89167.78 | L68: =J68-K68 -> 54651.22 | M68: =IF(J68=0,0,L68/J68) -> 0.38 | N68: 0.02 | O68: =J68*(1-N68) -> 140942.62 | P68: 13 | Q68: =IF(H68=0,0,P68/H68) -> 0.027027027 | R68: Danny Bell MD | S68: Q4 | T68: Yes
A69: SL00067 | B69: Aug | C69: 2022 | D69: USB-C Hub | E69: Accessories | F69: Lumbini | G69: Government | H69: 460 | I69: 3999 | J69: =H69*I69 -> 1839540 | K69: =J69*0.67 -> 1232491.8 | L69: =J69-K69 -> 607048.2 | M69: =IF(J69=0,0,L69/J69) -> 0.33 | N69: 0.13 | O69: =J69*(1-N69) -> 1600399.8 | P69: 2 | Q69: =IF(H69=0,0,P69/H69) -> 0.0043478261 | R69: Sherri Perez | S69: Q3 | T69: Yes
A70: SL00068 | B70: Jun | C70: 2024 | D70: Drawing Tablet | E70: Input | F70: Sudurpashchim | G70: Retail Store | H70: 368 | I70: 3999 | J70: =H70*I70 -> 1471632 | K70: =J70*0.48 -> 706383.36 | L70: =J70-K70 -> 765248.64 | M70: =IF(J70=0,0,L70/J70) -> 0.52 | N70: 0.02 | O70: =J70*(1-N70) -> 1442199.4 | P70: 14 | Q70: =IF(H70=0,0,P70/H70) -> 0.038043478 | R70: Allison Casey | S70: Q2 | T70: Yes
A71: SL00069 | B71: Feb | C71: 2024 | D71: Portable Charger | E71: Accessories | F71: Lumbini | G71: Government | H71: 314 | I71: 12999 | J71: =H71*I71 -> 4081686 | K71: =J71*0.54 -> 2204110.4 | L71: =J71-K71 -> 1877575.6 | M71: =IF(J71=0,0,L71/J71) -> 0.46 | N71: 0.06 | O71: =J71*(1-N71) -> 3836784.8 | P71: 5 | Q71: =IF(H71=0,0,P71/H71) -> 0.015923567 | R71: Lee Gray | S71: Q1 | T71: Yes
A72: SL00070 | B72: Oct | C72: 2024 | D72: Cable Organiser | E72: Accessories | F72: Gandaki | G72: Retail Store | H72: 445 | I72: 12999 | J72: =H72*I72 -> 5784555 | K72: =J72*0.49 -> 2834432 | L72: =J72-K72 -> 2950123 | M72: =IF(J72=0,0,L72/J72) -> 0.51 | N72: 0.11 | O72: =J72*(1-N72) -> 5148254 | P72: 13 | Q72: =IF(H72=0,0,P72/H72) -> 0.029213483 | R72: Alicia Olson | S72: Q4 | T72: Yes
A73: SL00071 | B73: May | C73: 2024 | D73: LED Desk Lamp | E73: Accessories | F73: Lumbini | G73: Wholesale | H73: 321 | I73: 12999 | J73: =H73*I73 -> 4172679 | K73: =J73*0.48 -> 2002885.9 | L73: =J73-K73 -> 2169793.1 | M73: =IF(J73=0,0,L73/J73) -> 0.52 | N73: 0.02 | O73: =J73*(1-N73) -> 4089225.4 | P73: 6 | Q73: =IF(H73=0,0,P73/H73) -> 0.018691589 | R73: James Martinez | S73: Q2 | T73: Yes
A74: SL00072 | B74: Oct | C74: 2023 | D74: Laptop Pro X | E74: Computing | F74: Lumbini | G74: Corporate | H74: 438 | I74: 9999 | J74: =H74*I74 -> 4379562 | K74: =J74*0.59 -> 2583941.6 | L74: =J74-K74 -> 1795620.4 | M74: =IF(J74=0,0,L74/J74) -> 0.41 | N74: 0 | O74: =J74*(1-N74) -> 4379562 | P74: 15 | Q74: =IF(H74=0,0,P74/H74) -> 0.034246575 | R74: Kirsten Wilson | S74: Q4 | T74: Yes
A75: SL00073 | B75: Apr | C75: 2024 | D75: Drawing Tablet | E75: Input | F75: Lumbini | G75: Corporate | H75: 210 | I75: 9999 | J75: =H75*I75 -> 2099790 | K75: =J75*0.47 -> 986901.3 | L75: =J75-K75 -> 1112888.7 | M75: =IF(J75=0,0,L75/J75) -> 0.53 | N75: 0.09 | O75: =J75*(1-N75) -> 1910808.9 | P75: 3 | Q75: =IF(H75=0,0,P75/H75) -> 0.014285714 | R75: Luis Berger | S75: Q2 | T75: Yes
A76: SL00074 | B76: Oct | C76: 2024 | D76: Cooling Pad | E76: Accessories | F76: Karnali | G76: Retail Store | H76: 26 | I76: 12999 | J76: =H76*I76 -> 337974 | K76: =J76*0.49 -> 165607.26 | L76: =J76-K76 -> 172366.74 | M76: =IF(J76=0,0,L76/J76) -> 0.51 | N76: 0.1 | O76: =J76*(1-N76) -> 304176.6 | P76: 0 | Q76: =IF(H76=0,0,P76/H76) -> 0 | R76: Greg Hull | S76: Q4 | T76: Yes
A77: SL00075 | B77: Jan | C77: 2024 | D77: Smart Headset | E77: Audio | F77: Karnali | G77: Government | H77: 153 | I77: 8999 | J77: =H77*I77 -> 1376847 | K77: =J77*0.68 -> 936255.96 | L77: =J77-K77 -> 440591.04 | M77: =IF(J77=0,0,L77/J77) -> 0.32 | N77: 0.01 | O77: =J77*(1-N77) -> 1363078.5 | P77: 6 | Q77: =IF(H77=0,0,P77/H77) -> 0.039215686 | R77: Brandon Smith | S77: Q1 | T77: Yes
A78: SL00076 | B78: Mar | C78: 2024 | D78: 4K Monitor | E78: Display | F78: Madhesh | G78: Government | H78: 294 | I78: 2999 | J78: =H78*I78 -> 881706 | K78: =J78*0.59 -> 520206.54 | L78: =J78-K78 -> 361499.46 | M78: =IF(J78=0,0,L78/J78) -> 0.41 | N78: 0.14 | O78: =J78*(1-N78) -> 758267.16 | P78: 11 | Q78: =IF(H78=0,0,P78/H78) -> 0.037414966 | R78: Paul Morton | S78: Q1 | T78: Yes
A79: SL00077 | B79: Jan | C79: 2022 | D79: LED Desk Lamp | E79: Accessories | F79: Koshi | G79: Wholesale | H79: 189 | I79: 299 | J79: =H79*I79 -> 56511 | K79: =J79*0.54 -> 30515.94 | L79: =J79-K79 -> 25995.06 | M79: =IF(J79=0,0,L79/J79) -> 0.46 | N79: 0.01 | O79: =J79*(1-N79) -> 55945.89 | P79: 6 | Q79: =IF(H79=0,0,P79/H79) -> 0.031746032 | R79: Amber Pham | S79: Q1 | T79: Yes
A80: SL00078 | B80: May | C80: 2023 | D80: USB-C Hub | E80: Accessories | F80: Bagmati | G80: Wholesale | H80: 169 | I80: 1999 | J80: =H80*I80 -> 337831 | K80: =J80*0.55 -> 185807.05 | L80: =J80-K80 -> 152023.95 | M80: =IF(J80=0,0,L80/J80) -> 0.45 | N80: 0.03 | O80: =J80*(1-N80) -> 327696.07 | P80: 3 | Q80: =IF(H80=0,0,P80/H80) -> 0.017751479 | R80: Danielle Brown | S80: Q2 | T80: Yes
A81: SL00079 | B81: Feb | C81: 2024 | D81: Portable Charger | E81: Accessories | F81: Sudurpashchim | G81: Government | H81: 45 | I81: 9999 | J81: =H81*I81 -> 449955 | K81: =J81*0.63 -> 283471.65 | L81: =J81-K81 -> 166483.35 | M81: =IF(J81=0,0,L81/J81) -> 0.37 | N81: 0.09 | O81: =J81*(1-N81) -> 409459.05 | P81: 2 | Q81: =IF(H81=0,0,P81/H81) -> 0.044444444 | R81: Jeffrey Campbell | S81: Q1 | T81: Yes
A82: SL00080 | B82: Jul | C82: 2024 | D82: Cable Organiser | E82: Accessories | F82: Koshi | G82: Wholesale | H82: 270 | I82: 11999 | J82: =H82*I82 -> 3239730 | K82: =J82*0.7 -> 2267811 | L82: =J82-K82 -> 971919 | M82: =IF(J82=0,0,L82/J82) -> 0.3 | N82: 0.05 | O82: =J82*(1-N82) -> 3077743.5 | P82: 2 | Q82: =IF(H82=0,0,P82/H82) -> 0.0074074074 | R82: Lance Zamora | S82: Q3 | T82: No
A83: SL00081 | B83: Sep | C83: 2024 | D83: Drawing Tablet | E83: Input | F83: Lumbini | G83: Corporate | H83: 414 | I83: 12999 | J83: =H83*I83 -> 5381586 | K83: =J83*0.67 -> 3605662.6 | L83: =J83-K83 -> 1775923.4 | M83: =IF(J83=0,0,L83/J83) -> 0.33 | N83: 0.03 | O83: =J83*(1-N83) -> 5220138.4 | P83: 9 | Q83: =IF(H83=0,0,P83/H83) -> 0.02173913 | R83: Mrs. Jennifer Sandoval DDS | S83: Q3 | T83: Yes
A84: SL00082 | B84: Jan | C84: 2022 | D84: Laptop Pro X | E84: Computing | F84: Lumbini | G84: Online | H84: 378 | I84: 799 | J84: =H84*I84 -> 302022 | K84: =J84*0.5 -> 151011 | L84: =J84-K84 -> 151011 | M84: =IF(J84=0,0,L84/J84) -> 0.5 | N84: 0.09 | O84: =J84*(1-N84) -> 274840.02 | P84: 13 | Q84: =IF(H84=0,0,P84/H84) -> 0.034391534 | R84: Todd Harris | S84: Q1 | T84: No
A85: SL00083 | B85: Jan | C85: 2023 | D85: Webcam HD | E85: Peripherals | F85: Madhesh | G85: Retail Store | H85: 6 | I85: 24999 | J85: =H85*I85 -> 149994 | K85: =J85*0.5 -> 74997 | L85: =J85-K85 -> 74997 | M85: =IF(J85=0,0,L85/J85) -> 0.5 | N85: 0.04 | O85: =J85*(1-N85) -> 143994.24 | P85: 0 | Q85: =IF(H85=0,0,P85/H85) -> 0 | R85: Robin Hurst | S85: Q1 | T85: Yes
A86: SL00084 | B86: May | C86: 2024 | D86: Cooling Pad | E86: Accessories | F86: Koshi | G86: Online | H86: 59 | I86: 24999 | J86: =H86*I86 -> 1474941 | K86: =J86*0.53 -> 781718.73 | L86: =J86-K86 -> 693222.27 | M86: =IF(J86=0,0,L86/J86) -> 0.47 | N86: 0.06 | O86: =J86*(1-N86) -> 1386444.5 | P86: 2 | Q86: =IF(H86=0,0,P86/H86) -> 0.033898305 | R86: Jill Turner | S86: Q2 | T86: Yes
A87: SL00085 | B87: Mar | C87: 2022 | D87: Webcam HD | E87: Peripherals | F87: Karnali | G87: Wholesale | H87: 473 | I87: 24999 | J87: =H87*I87 -> 11824527 | K87: =J87*0.57 -> 6739980.4 | L87: =J87-K87 -> 5084546.6 | M87: =IF(J87=0,0,L87/J87) -> 0.43 | N87: 0.07 | O87: =J87*(1-N87) -> 10996810 | P87: 1 | Q87: =IF(H87=0,0,P87/H87) -> 0.0021141649 | R87: Juan Melton | S87: Q1 | T87: Yes
A88: SL00086 | B88: Aug | C88: 2022 | D88: Drawing Tablet | E88: Input | F88: Lumbini | G88: Government | H88: 459 | I88: 8999 | J88: =H88*I88 -> 4130541 | K88: =J88*0.57 -> 2354408.4 | L88: =J88-K88 -> 1776132.6 | M88: =IF(J88=0,0,L88/J88) -> 0.43 | N88: 0.12 | O88: =J88*(1-N88) -> 3634876.1 | P88: 1 | Q88: =IF(H88=0,0,P88/H88) -> 0.0021786492 | R88: Steven Flores | S88: Q3 | T88: Yes
A89: SL00087 | B89: Oct | C89: 2024 | D89: Drawing Tablet | E89: Input | F89: Koshi | G89: Government | H89: 275 | I89: 4999 | J89: =H89*I89 -> 1374725 | K89: =J89*0.5 -> 687362.5 | L89: =J89-K89 -> 687362.5 | M89: =IF(J89=0,0,L89/J89) -> 0.5 | N89: 0.1 | O89: =J89*(1-N89) -> 1237252.5 | P89: 12 | Q89: =IF(H89=0,0,P89/H89) -> 0.043636364 | R89: Ashley Reed | S89: Q4 | T89: Yes
A90: SL00088 | B90: Feb | C90: 2022 | D90: 4K Monitor | E90: Display | F90: Karnali | G90: Online | H90: 174 | I90: 15999 | J90: =H90*I90 -> 2783826 | K90: =J90*0.61 -> 1698133.9 | L90: =J90-K90 -> 1085692.1 | M90: =IF(J90=0,0,L90/J90) -> 0.39 | N90: 0.13 | O90: =J90*(1-N90) -> 2421928.6 | P90: 6 | Q90: =IF(H90=0,0,P90/H90) -> 0.034482759 | R90: Trevor Tucker | S90: Q1 | T90: Yes
A91: SL00089 | B91: Oct | C91: 2022 | D91: Cable Organiser | E91: Accessories | F91: Karnali | G91: Wholesale | H91: 362 | I91: 799 | J91: =H91*I91 -> 289238 | K91: =J91*0.53 -> 153296.14 | L91: =J91-K91 -> 135941.86 | M91: =IF(J91=0,0,L91/J91) -> 0.47 | N91: 0 | O91: =J91*(1-N91) -> 289238 | P91: 13 | Q91: =IF(H91=0,0,P91/H91) -> 0.035911602 | R91: Thomas Skinner | S91: Q4 | T91: Yes
A92: SL00090 | B92: Aug | C92: 2022 | D92: Webcam HD | E92: Peripherals | F92: Lumbini | G92: Wholesale | H92: 111 | I92: 1999 | J92: =H92*I92 -> 221889 | K92: =J92*0.53 -> 117601.17 | L92: =J92-K92 -> 104287.83 | M92: =IF(J92=0,0,L92/J92) -> 0.47 | N92: 0.02 | O92: =J92*(1-N92) -> 217451.22 | P92: 0 | Q92: =IF(H92=0,0,P92/H92) -> 0 | R92: Elizabeth Tran | S92: Q3 | T92: Yes
A93: SL00091 | B93: Feb | C93: 2023 | D93: Cooling Pad | E93: Accessories | F93: Bagmati | G93: Corporate | H93: 464 | I93: 1999 | J93: =H93*I93 -> 927536 | K93: =J93*0.49 -> 454492.64 | L93: =J93-K93 -> 473043.36 | M93: =IF(J93=0,0,L93/J93) -> 0.51 | N93: 0.05 | O93: =J93*(1-N93) -> 881159.2 | P93: 15 | Q93: =IF(H93=0,0,P93/H93) -> 0.032327586 | R93: Nathaniel French | S93: Q1 | T93: Yes
A94: SL00092 | B94: Jun | C94: 2022 | D94: LED Desk Lamp | E94: Accessories | F94: Karnali | G94: Online | H94: 421 | I94: 1999 | J94: =H94*I94 -> 841579 | K94: =J94*0.62 -> 521778.98 | L94: =J94-K94 -> 319800.02 | M94: =IF(J94=0,0,L94/J94) -> 0.38 | N94: 0.02 | O94: =J94*(1-N94) -> 824747.42 | P94: 1 | Q94: =IF(H94=0,0,P94/H94) -> 0.0023752969 | R94: David Alexander | S94: Q2 | T94: No
A95: SL00093 | B95: Jul | C95: 2024 | D95: Cable Organiser | E95: Accessories | F95: Madhesh | G95: Online | H95: 3 | I95: 35999 | J95: =H95*I95 -> 107997 | K95: =J95*0.68 -> 73437.96 | L95: =J95-K95 -> 34559.04 | M95: =IF(J95=0,0,L95/J95) -> 0.32 | N95: 0.1 | O95: =J95*(1-N95) -> 97197.3 | P95: 0 | Q95: =IF(H95=0,0,P95/H95) -> 0 | R95: Tiffany Smith | S95: Q3 | T95: Yes
A96: SL00094 | B96: Aug | C96: 2022 | D96: Wireless Mouse | E96: Peripherals | F96: Madhesh | G96: Wholesale | H96: 12 | I96: 11999 | J96: =H96*I96 -> 143988 | K96: =J96*0.64 -> 92152.32 | L96: =J96-K96 -> 51835.68 | M96: =IF(J96=0,0,L96/J96) -> 0.36 | N96: 0.1 | O96: =J96*(1-N96) -> 129589.2 | P96: 0 | Q96: =IF(H96=0,0,P96/H96) -> 0 | R96: Debra Chapman | S96: Q3 | T96: Yes
A97: SL00095 | B97: Apr | C97: 2022 | D97: 4K Monitor | E97: Display | F97: Koshi | G97: Government | H97: 164 | I97: 2999 | J97: =H97*I97 -> 491836 | K97: =J97*0.56 -> 275428.16 | L97: =J97-K97 -> 216407.84 | M97: =IF(J97=0,0,L97/J97) -> 0.44 | N97: 0.02 | O97: =J97*(1-N97) -> 481999.28 | P97: 2 | Q97: =IF(H97=0,0,P97/H97) -> 0.012195122 | R97: Vincent Brown | S97: Q2 | T97: Yes
A98: SL00096 | B98: May | C98: 2022 | D98: Laptop Pro X | E98: Computing | F98: Madhesh | G98: Government | H98: 264 | I98: 7999 | J98: =H98*I98 -> 2111736 | K98: =J98*0.5 -> 1055868 | L98: =J98-K98 -> 1055868 | M98: =IF(J98=0,0,L98/J98) -> 0.5 | N98: 0.05 | O98: =J98*(1-N98) -> 2006149.2 | P98: 5 | Q98: =IF(H98=0,0,P98/H98) -> 0.018939394 | R98: Janet Smith | S98: Q2 | T98: Yes
A99: SL00097 | B99: Mar | C99: 2024 | D99: LED Desk Lamp | E99: Accessories | F99: Koshi | G99: Government | H99: 126 | I99: 12999 | J99: =H99*I99 -> 1637874 | K99: =J99*0.47 -> 769800.78 | L99: =J99-K99 -> 868073.22 | M99: =IF(J99=0,0,L99/J99) -> 0.53 | N99: 0.09 | O99: =J99*(1-N99) -> 1490465.3 | P99: 2 | Q99: =IF(H99=0,0,P99/H99) -> 0.015873016 | R99: Jeremy Walker | S99: Q1 | T99: No
A100: SL00098 | B100: Jan | C100: 2022 | D100: Laptop Pro X | E100: Computing | F100: Lumbini | G100: Online | H100: 55 | I100: 15999 | J100: =H100*I100 -> 879945 | K100: =J100*0.46 -> 404774.7 | L100: =J100-K100 -> 475170.3 | M100: =IF(J100=0,0,L100/J100) -> 0.54 | N100: 0.06 | O100: =J100*(1-N100) -> 827148.3 | P100: 0 | Q100: =IF(H100=0,0,P100/H100) -> 0 | R100: Matthew Patel | S100: Q1 | T100: No
...

Sheet Student Records
A1: 🎓 Student Academic Records — 2024
A2: Student ID | B2: Full Name | C2: Program | D2: Semester | E2: Academic Year | F2: Subject 1 | G2: Sub1 Score | H2: Subject 2 | I2: Sub2 Score | J2: Subject 3 | K2: Sub3 Score | L2: Total Marks | M2: Percentage | N2: Grade | O2: GPA | P2: Attendance % | Q2: Assignment Score | R2: Practical Score | S2: Pass/Fail | T2: Scholarship?
A3: STU00001 | B3: Peter Allen | C3: BSc CSIT | D3: 1 | E3: 2022-23 | F3: English | G3: 57 | H3: Networking | I3: 92 | J3: Statistics | K3: 70 | L3: =G3+I3+K3 -> 219 | M3: =L3/300*100 -> 73 | N3: =IF(M3>=90,"A+",IF(M3>=80,"A",IF(M3>=70,"B+",IF(M3>=60,"B",IF(M3>=50,"C","F"))))) -> B+ | O3: =IF(M3>=90,4,IF(M3>=80,3.7,IF(M3>=70,3.3,IF(M3>=60,3,IF(M3>=50,2,0))))) -> 3.3 | P3: 0.573 | Q3: 40.5 | R3: 77.8 | S3: =IF(M3>=40,"Pass","Fail") -> Pass | T3: =IF(M3>=80,"Yes","No") -> No
A4: STU00002 | B4: Raymond Mccarthy | C4: BHM | D4: 7 | E4: 2022-23 | F4: Web Technology | G4: 24 | H4: Statistics | I4: 82 | J4: AI & ML | K4: 71 | L4: =G4+I4+K4 -> 177 | M4: =L4/300*100 -> 59 | N4: =IF(M4>=90,"A+",IF(M4>=80,"A",IF(M4>=70,"B+",IF(M4>=60,"B",IF(M4>=50,"C","F"))))) -> C | O4: =IF(M4>=90,4,IF(M4>=80,3.7,IF(M4>=70,3.3,IF(M4>=60,3,IF(M4>=50,2,0))))) -> 2 | P4: 0.769 | Q4: 75.5 | R4: 76.7 | S4: =IF(M4>=40,"Pass","Fail") -> Pass | T4: =IF(M4>=80,"Yes","No") -> No
A5: STU00003 | B5: Ryan Stewart | C5: BHM | D5: 8 | E5: 2021-22 | F5: Mathematics | G5: 74 | H5: Statistics | I5: 93 | J5: English | K5: 60 | L5: =G5+I5+K5 -> 227 | M5: =L5/300*100 -> 75.666667 | N5: =IF(M5>=90,"A+",IF(M5>=80,"A",IF(M5>=70,"B+",IF(M5>=60,"B",IF(M5>=50,"C","F"))))) -> B+ | O5: =IF(M5>=90,4,IF(M5>=80,3.7,IF(M5>=70,3.3,IF(M5>=60,3,IF(M5>=50,2,0))))) -> 3.3 | P5: 0.799 | Q5: 56.1 | R5: 78.9 | S5: =IF(M5>=40,"Pass","Fail") -> Pass | T5: =IF(M5>=80,"Yes","No") -> No
A6: STU00004 | B6: Larry Lewis | C6: BSc CSIT | D6: 2 | E6: 2022-23 | F6: English | G6: 75 | H6: Software Engineering | I6: 22 | J6: Web Technology | K6: 40 | L6: =G6+I6+K6 -> 137 | M6: =L6/300*100 -> 45.666667 | N6: =IF(M6>=90,"A+",IF(M6>=80,"A",IF(M6>=70,"B+",IF(M6>=60,"B",IF(M6>=50,"C","F"))))) -> F | O6: =IF(M6>=90,4,IF(M6>=80,3.7,IF(M6>=70,3.3,IF(M6>=60,3,IF(M6>=50,2,0))))) -> 0 | P6: 0.68 | Q6: 51.5 | R6: 60.6 | S6: =IF(M6>=40,"Pass","Fail") -> Pass | T6: =IF(M6>=80,"Yes","No") -> No
A7: STU00005 | B7: Mark Ramirez | C7: BIT | D7: 4 | E7: 2023-24 | F7: Software Engineering | G7: 57 | H7: Web Technology | I7: 69 | J7: Database | K7: 73 | L7: =G7+I7+K7 -> 199 | M7: =L7/300*100 -> 66.333333 | N7: =IF(M7>=90,"A+",IF(M7>=80,"A",IF(M7>=70,"B+",IF(M7>=60,"B",IF(M7>=50,"C","F"))))) -> B | O7: =IF(M7>=90,4,IF(M7>=80,3.7,IF(M7>=70,3.3,IF(M7>=60,3,IF(M7>=50,2,0))))) -> 3 | P7: 0.925 | Q7: 80.4 | R7: 84.1 | S7: =IF(M7>=40,"Pass","Fail") -> Pass | T7: =IF(M7>=80,"Yes","No") -> No
A8: STU00006 | B8: Jeffrey Alexander | C8: B.Eng | D8: 8 | E8: 2021-22 | F8: English | G8: 31 | H8: Networking | I8: 81 | J8: AI & ML | K8: 36 | L8: =G8+I8+K8 -> 148 | M8: =L8/300*100 -> 49.333333 | N8: =IF(M8>=90,"A+",IF(M8>=80,"A",IF(M8>=70,"B+",IF(M8>=60,"B",IF(M8>=50,"C","F"))))) -> F | O8: =IF(M8>=90,4,IF(M8>=80,3.7,IF(M8>=70,3.3,IF(M8>=60,3,IF(M8>=50,2,0))))) -> 0 | P8: 0.628 | Q8: 49.4 | R8: 69.5 | S8: =IF(M8>=40,"Pass","Fail") -> Pass | T8: =IF(M8>=80,"Yes","No") -> No
A9: STU00007 | B9: Danielle Martinez | C9: B.Eng | D9: 7 | E9: 2022-23 | F9: AI & ML | G9: 91 | H9: Networking | I9: 26 | J9: Statistics | K9: 22 | L9: =G9+I9+K9 -> 139 | M9: =L9/300*100 -> 46.333333 | N9: =IF(M9>=90,"A+",IF(M9>=80,"A",IF(M9>=70,"B+",IF(M9>=60,"B",IF(M9>=50,"C","F"))))) -> F | O9: =IF(M9>=90,4,IF(M9>=80,3.7,IF(M9>=70,3.3,IF(M9>=60,3,IF(M9>=50,2,0))))) -> 0 | P9: 0.711 | Q9: 55.6 | R9: 80.6 | S9: =IF(M9>=40,"Pass","Fail") -> Pass | T9: =IF(M9>=80,"Yes","No") -> No
A10: STU00008 | B10: Marissa Thompson | C10: BIT | D10: 1 | E10: 2021-22 | F10: Software Engineering | G10: 99 | H10: Operating System | I10: 49 | J10: Programming | K10: 35 | L10: =G10+I10+K10 -> 183 | M10: =L10/300*100 -> 61 | N10: =IF(M10>=90,"A+",IF(M10>=80,"A",IF(M10>=70,"B+",IF(M10>=60,"B",IF(M10>=50,"C","F"))))) -> B | O10: =IF(M10>=90,4,IF(M10>=80,3.7,IF(M10>=70,3.3,IF(M10>=60,3,IF(M10>=50,2,0))))) -> 3 | P10: 0.803 | Q10: 69.2 | R10: 99.6 | S10: =IF(M10>=40,"Pass","Fail") -> Pass | T10: =IF(M10>=80,"Yes","No") -> No
A11: STU00009 | B11: Savannah Townsend | C11: B.Eng | D11: 6 | E11: 2021-22 | F11: Statistics | G11: 85 | H11: AI & ML | I11: 97 | J11: Database | K11: 33 | L11: =G11+I11+K11 -> 215 | M11: =L11/300*100 -> 71.666667 | N11: =IF(M11>=90,"A+",IF(M11>=80,"A",IF(M11>=70,"B+",IF(M11>=60,"B",IF(M11>=50,"C","F"))))) -> B+ | O11: =IF(M11>=90,4,IF(M11>=80,3.7,IF(M11>=70,3.3,IF(M11>=60,3,IF(M11>=50,2,0))))) -> 3.3 | P11: 0.868 | Q11: 95.6 | R11: 66.3 | S11: =IF(M11>=40,"Pass","Fail") -> Pass | T11: =IF(M11>=80,"Yes","No") -> No
A12: STU00010 | B12: Jeff Jensen | C12: BSc CSIT | D12: 2 | E12: 2021-22 | F12: English | G12: 84 | H12: Programming | I12: 33 | J12: Mathematics | K12: 41 | L12: =G12+I12+K12 -> 158 | M12: =L12/300*100 -> 52.666667 | N12: =IF(M12>=90,"A+",IF(M12>=80,"A",IF(M12>=70,"B+",IF(M12>=60,"B",IF(M12>=50,"C","F"))))) -> C | O12: =IF(M12>=90,4,IF(M12>=80,3.7,IF(M12>=70,3.3,IF(M12>=60,3,IF(M12>=50,2,0))))) -> 2 | P12: 0.833 | Q12: 92.3 | R12: 94.7 | S12: =IF(M12>=40,"Pass","Fail") -> Pass | T12: =IF(M12>=80,"Yes","No") -> No
A13: STU00011 | B13: Tammie Lee | C13: BIT | D13: 5 | E13: 2023-24 | F13: Web Technology | G13: 32 | H13: Statistics | I13: 39 | J13: English | K13: 66 | L13: =G13+I13+K13 -> 137 | M13: =L13/300*100 -> 45.666667 | N13: =IF(M13>=90,"A+",IF(M13>=80,"A",IF(M13>=70,"B+",IF(M13>=60,"B",IF(M13>=50,"C","F"))))) -> F | O13: =IF(M13>=90,4,IF(M13>=80,3.7,IF(M13>=70,3.3,IF(M13>=60,3,IF(M13>=50,2,0))))) -> 0 | P13: 0.701 | Q13: 48.3 | R13: 90.9 | S13: =IF(M13>=40,"Pass","Fail") -> Pass | T13: =IF(M13>=80,"Yes","No") -> No
A14: STU00012 | B14: Timothy Cowan | C14: BSc CSIT | D14: 7 | E14: 2021-22 | F14: Networking | G14: 56 | H14: Web Technology | I14: 84 | J14: Software Engineering | K14: 41 | L14: =G14+I14+K14 -> 181 | M14: =L14/300*100 -> 60.333333 | N14: =IF(M14>=90,"A+",IF(M14>=80,"A",IF(M14>=70,"B+",IF(M14>=60,"B",IF(M14>=50,"C","F"))))) -> B | O14: =IF(M14>=90,4,IF(M14>=80,3.7,IF(M14>=70,3.3,IF(M14>=60,3,IF(M14>=50,2,0))))) -> 3 | P14: 0.588 | Q14: 62.3 | R14: 85.3 | S14: =IF(M14>=40,"Pass","Fail") -> Pass | T14: =IF(M14>=80,"Yes","No") -> No
... A402: STU00400 | B402: Kimberly Bishop | C402: BHM | D402: 5 | E402: 2021-22 | F402: Software Engineering | G402: 31 | H402: Statistics | I402: 85 | J402: AI & ML | K402: 46 | L402: =G402+I402+K402 -> 162 | M402: =L402/300*100 -> 54 | N402: =IF(M402>=90,"A+",IF(M402>=80,"A",IF(M402>=70,"B+",IF(M402>=60,"B",IF(M402>=50,"C","F"))))) -> C | O402: =IF(M402>=90,4,IF(M402>=80,3.7,IF(M402>=70,3.3,IF(M402>=60,3,IF(M402>=50,2,0))))) -> 2 | P402: 0.666 | Q402: 68.1 | R402: 41.9 | S402: =IF(M402>=40,"Pass","Fail") -> Pass | T402: =IF(M402>=80,"Yes","No") -> No
A403: AVERAGES | G403: =AVERAGE(G3:G402) -> 58.205 | I403: =AVERAGE(I3:I402) -> 60.94 | K403: =AVERAGE(K3:K402) -> 59.7 | L403: =AVERAGE(L3:L402) -> 178.845 | M403: =AVERAGE(M3:M402) -> 59.615 | O403: =AVERAGE(O3:O402) -> 2.143 | P403: =AVERAGE(P3:P402) -> 0.7638225

Sheet Inventory
A1: 📦 Inventory & Stock Management
A2: SKU | B2: Product Name | C2: Category | D2: Supplier | E2: Unit Cost (NPR) | F2: Selling Price (NPR) | G2: Markup % | H2: Stock Qty | I2: Reorder Level | J2: Stock Value (NPR) | K2: Last Restocked | L2: Avg Monthly Sales | M2: Months of Stock | N2: Status | O2: Location | P2: Condition | Q2: Warranty (Months) | R2: Weight (kg) | S2: In Transit | T2: Total Assets (NPR)
A3: SKU0001 | B3: Laptop Pro 15 | C3: Electronics | D3: Digital Hub | E3: 86700 | F3: 147800 | G3: =(F3-E3)/E3 -> 0.70472895 | H3: 243 | I3: 13 | J3: =H3*E3 -> 21068100 | K3: 45348 | L3: 37.9 | M3: =IF(L3=0,"N/A",TEXT(H3/L3,"0.0")) -> 6.4 | N3: =IF(H3=0,"Out of Stock",IF(H3<I3,"Low Stock","In Stock")) -> In Stock | O3: Overflow | P3: New | Q3: 24 | R3: 5.65 | S3: 10 | T3: =(H3+S3)*E3 -> 21935100
A4: SKU0002 | B4: Laptop Air 13 | C4: Networking | D4: Prime Wholesale | E4: 14200 | F4: 24200 | G4: =(F4-E4)/E4 -> 0.70422535 | H4: 445 | I4: 5 | J4: =H4*E4 -> 6319000 | K4: 45613 | L4: 13.5 | M4: =IF(L4=0,"N/A",TEXT(H4/L4,"0.0")) -> 33.0 | N4: =IF(H4=0,"Out of Stock",IF(H4<I4,"Low Stock","In Stock")) -> In Stock | O4: Warehouse B | P4: New | Q4: 6 | R4: 5.09 | S4: 15 | T4: =(H4+S4)*E4 -> 6532000
A5: SKU0003 | B5: Gaming PC Tower | C5: Networking | D5: Himalayan Distributors | E5: 61600 | F5: 100900 | G5: =(F5-E5)/E5 -> 0.63798701 | H5: 385 | I5: 6 | J5: =H5*E5 -> 23716000 | K5: 45567 | L5: 35.7 | M5: =IF(L5=0,"N/A",TEXT(H5/L5,"0.0")) -> 10.8 | N5: =IF(H5=0,"Out of Stock",IF(H5<I5,"Low Stock","In Stock")) -> In Stock | O5: Cold Storage | P5: Refurbished | Q5: 36 | R5: 6.9 | S5: 19 | T5: =(H5+S5)*E5 -> 24886400
A6: SKU0004 | B6: Mini PC | C6: Storage | D6: Alpha Traders | E6: 32400 | F6: 45400 | G6: =(F6-E6)/E6 -> 0.40123457 | H6: 191 | I6: 43 | J6: =H6*E6 -> 6188400 | K6: 45554 | L6: 27.7 | M6: =IF(L6=0,"N/A",TEXT(H6/L6,"0.0")) -> 6.9 | N6: =IF(H6=0,"Out of Stock",IF(H6<I6,"Low Stock","In Stock")) -> In Stock | O6: Warehouse B | P6: Damaged | Q6: 6 | R6: 6.08 | S6: 21 | T6: =(H6+S6)*E6 -> 6868800
A7: SKU0005 | B7: Workstation Elite | C7: Electronics | D7: Star Imports | E7: 56300 | F7: 102400 | G7: =(F7-E7)/E7 -> 0.81882771 | H7: 488 | I7: 41 | J7: =H7*E7 -> 27474400 | K7: 45611 | L7: 32.7 | M7: =IF(L7=0,"N/A",TEXT(H7/L7,"0.0")) -> 14.9 | N7: =IF(H7=0,"Out of Stock",IF(H7<I7,"Low Stock","In Stock")) -> In Stock | O7: Showroom | P7: Damaged | Q7: 12 | R7: 2.54 | S7: 0 | T7: =(H7+S7)*E7 -> 27474400
A8: SKU0006 | B8: Wireless Mouse Pro | C8: Audio | D8: Digital Hub | E8: 26500 | F8: 52000 | G8: =(F8-E8)/E8 -> 0.96226415 | H8: 290 | I8: 13 | J8: =H8*E8 -> 7685000 | K8: 45638 | L8: 11.3 | M8: =IF(L8=0,"N/A",TEXT(H8/L8,"0.0")) -> 25.7 | N8: =IF(H8=0,"Out of Stock",IF(H8<I8,"Low Stock","In Stock")) -> In Stock | O8: Warehouse A | P8: New | Q8: 6 | R8: 11.85 | S8: 10 | T8: =(H8+S8)*E8 -> 7950000
A9: SKU0007 | B9: Mechanical KB RGB | C9: Computing | D9: Alpha Traders | E9: 19000 | F9: 35000 | G9: =(F9-E9)/E9 -> 0.84210526 | H9: 234 | I9: 30 | J9: =H9*E9 -> 4446000 | K9: 45306 | L9: 14.1 | M9: =IF(L9=0,"N/A",TEXT(H9/L9,"0.0")) -> 16.6 | N9: =IF(H9=0,"Out of Stock",IF(H9<I9,"Low Stock","In Stock")) -> In Stock | O9: Warehouse B | P9: New | Q9: 12 | R9: 9.91 | S9: 0 | T9: =(H9+S9)*E9 -> 4446000
A10: SKU0008 | B10: Trackpad Plus | C10: Networking | D10: TechNepal Pvt Ltd | E10: 24600 | F10: 34200 | G10: =(F10-E10)/E10 -> 0.3902439 | H10: 104 | I10: 32 | J10: =H10*E10 -> 2558400 | K10: 45597 | L10: 8.1 | M10: =IF(L10=0,"N/A",TEXT(H10/L10,"0.0")) -> 12.8 | N10: =IF(H10=0,"Out of Stock",IF(H10<I10,"Low Stock","In Stock")) -> In Stock | O10: Showroom | P10: New | Q10: 36 | R10: 2.4 | S10: 7 | T10: =(H10+S10)*E10 -> 2730600
A11: SKU0009 | B11: Numpad Slim | C11: Storage | D11: Himalayan Distributors | E11: 45600 | F11: 58400 | G11: =(F11-E11)/E11 -> 0.28070175 | H11: 281 | I11: 48 | J11: =H11*E11 -> 12813600 | K11: 45385 | L11: 32.1 | M11: =IF(L11=0,"N/A",TEXT(H11/L11,"0.0")) -> 8.8 | N11: =IF(H11=0,"Out of Stock",IF(H11<I11,"Low Stock","In Stock")) -> In Stock | O11: Cold Storage | P11: New | Q11: 24 | R11: 13.7 | S11: 6 | T11: =(H11+S11)*E11 -> 13087200
A12: SKU0010 | B12: Wrist Rest | C12: Computing | D12: TechNepal Pvt Ltd | E12: 51300 | F12: 66800 | G12: =(F12-E12)/E12 -> 0.30214425 | H12: 390 | I12: 13 | J12: =H12*E12 -> 20007000 | K12: 45520 | L12: 32.6 | M12: =IF(L12=0,"N/A",TEXT(H12/L12,"0.0")) -> 12.0 | N12: =IF(H12=0,"Out of Stock",IF(H12<I12,"Low Stock","In Stock")) -> In Stock | O12: Overflow | P12: Refurbished | Q12: 24 | R12: 13.48 | S12: 10 | T12: =(H12+S12)*E12 -> 20520000
A13: SKU0011 | B13: 24" FHD Monitor | C13: Display | D13: TechNepal Pvt Ltd | E13: 45900 | F13: 73000 | G13: =(F13-E13)/E13 -> 0.59041394 | H13: 379 | I13: 42 | J13: =H13*E13 -> 17396100 | K13: 45447 | L13: 3.1 | M13: =IF(L13=0,"N/A",TEXT(H13/L13,"0.0")) -> 122.3 | N13: =IF(H13=0,"Out of Stock",IF(H13<I13,"Low Stock","In Stock")) -> In Stock | O13: Showroom | P13: New | Q13: 12 | R13: 9.17 | S13: 28 | T13: =(H13+S13)*E13 -> 18681300
A14: SKU0012 | B14: 27" QHD Monitor | C14: Networking | D14: Digital Hub | E14: 108400 | F14: 130200 | G14: =(F14-E14)/E14 -> 0.20110701 | H14: 306 | I14: 30 | J14: =H14*E14 -> 33170400 | K14: 45353 | L14: 73.3 | M14: =IF(L14=0,"N/A",TEXT(H14/L14,"0.0")) -> 4.2 | N14: =IF(H14=0,"Out of Stock",IF(H14<I14,"Low Stock","In Stock")) -> In Stock | O14: Warehouse B | P14: New | Q14: 24 | R14: 3.53 | S14: 20 | T14: =(H14+S14)*E14 -> 35338400
... A252: SKU0250 | B252: Desk Organiser | C252: Electronics | D252: Prime Wholesale | E252: 74300 | F252: 117700 | G252: =(F252-E252)/E252 -> 0.58411844 | H252: 374 | I252: 49 | J252: =H252*E252 -> 27788200 | K252: 45574 | L252: 13.1 | M252: =IF(L252=0,"N/A",TEXT(H252/L252,"0.0")) -> 28.5 | N252: =IF(H252=0,"Out of Stock",IF(H252<I252,"Low Stock","In Stock")) -> In Stock | O252: Warehouse A | P252: New | Q252: 24 | R252: 6.02 | S252: 2 | T252: =(H252+S252)*E252 -> 27936800
A253: TOTALS | H253: =SUM(H3:H252) -> 63870 | J253: =SUM(J3:J252) -> 3606432600 | T253: =SUM(T3:T252) -> 3827058500
